{
  "products": [
    {
      "id": "fitness-reality-810xlt",
      "name": "Fitness Reality 810XLT Power Cage",
      "brand": "Fitness Reality",
      "tier": "budget",
      "price": 300,
      "priceDisplay": "$300",
      "asin": "B01NBOVAIJ",
      "amazonUrl": "https://www.amazon.com/dp/B01NBOVAIJ?tag=runbikecalc-20",
      "imageUrl": null,
      "imageMedium": null,
      "scores": {
        "goal_strength": 8, "goal_bodybuilding": 7, "goal_powerlifting": 4, "goal_functional": 5, "goal_general": 8,
        "exp_beginner": 9, "exp_intermediate": 7, "exp_advanced": 3,
        "lift_squat": 8, "lift_bench": 8, "lift_deadlift": 5, "lift_ohp": 7, "lift_pullup": 7,
        "space_compact": 6, "space_garage": 8, "space_dedicated": 8,
        "budget_under_500": 10, "budget_500_1000": 6, "budget_1000_2000": 2, "budget_over_2000": 1,
        "ceiling_under_8": 8, "ceiling_8_9": 9, "ceiling_over_9": 8
      },
      "specs": { "type": "Power Cage", "footprint": "50\" x 46\"", "height": "83.5\"", "weightCapacity": "800 lb", "pullUpBar": true, "jCups": true, "safetyBars": true },
      "verdict": { "garageGymReady": "YES", "bestFor": "Best budget full power cage" },
      "pairsWith": ["flat-bench", "olympic-barbell", "bumper-plates", "horse-stall-mat"]
    },
    {
      "id": "cap-power-rack",
      "name": "CAP Barbell Power Rack",
      "brand": "CAP",
      "tier": "budget",
      "price": 200,
      "priceDisplay": "$200",
      "asin": "B07GZF5JWW",
      "amazonUrl": "https://www.amazon.com/dp/B07GZF5JWW?tag=runbikecalc-20",
      "imageUrl": null,
      "imageMedium": null,
      "scores": {
        "goal_strength": 7, "goal_bodybuilding": 6, "goal_powerlifting": 3, "goal_functional": 4, "goal_general": 7,
        "exp_beginner": 9, "exp_intermediate": 5, "exp_advanced": 2,
        "lift_squat": 7, "lift_bench": 7, "lift_deadlift": 4, "lift_ohp": 6, "lift_pullup": 6,
        "space_compact": 7, "space_garage": 7, "space_dedicated": 6,
        "budget_under_500": 10, "budget_500_1000": 5, "budget_1000_2000": 1, "budget_over_2000": 0,
        "ceiling_under_8": 8, "ceiling_8_9": 9, "ceiling_over_9": 8
      },
      "specs": { "type": "Squat Stand / Light Cage", "footprint": "46\" x 42\"", "height": "82\"", "weightCapacity": "500 lb", "pullUpBar": true, "jCups": true, "safetyBars": true },
      "verdict": { "garageGymReady": "MAYBE", "bestFor": "Ultra-budget squat stand" },
      "pairsWith": ["flat-bench", "olympic-barbell", "bumper-plates"]
    },
    {
      "id": "titan-t2",
      "name": "Titan T-2 Series Power Rack",
      "brand": "Titan Fitness",
      "tier": "mid",
      "price": 450,
      "priceDisplay": "$450",
      "asin": "B00GHNLK9E",
      "amazonUrl": "https://www.amazon.com/dp/B00GHNLK9E?tag=runbikecalc-20",
      "imageUrl": null,
      "imageMedium": null,
      "scores": {
        "goal_strength": 8, "goal_bodybuilding": 8, "goal_powerlifting": 6, "goal_functional": 6, "goal_general": 8,
        "exp_beginner": 8, "exp_intermediate": 8, "exp_advanced": 5,
        "lift_squat": 9, "lift_bench": 9, "lift_deadlift": 5, "lift_ohp": 8, "lift_pullup": 8,
        "space_compact": 5, "space_garage": 9, "space_dedicated": 9,
        "budget_under_500": 9, "budget_500_1000": 8, "budget_1000_2000": 4, "budget_over_2000": 2,
        "ceiling_under_8": 6, "ceiling_8_9": 9, "ceiling_over_9": 9
      },
      "specs": { "type": "Power Rack", "footprint": "48\" x 48\"", "height": "83\"", "weightCapacity": "700 lb", "pullUpBar": true, "jCups": true, "safetyBars": true },
      "verdict": { "garageGymReady": "YES", "bestFor": "Best value mid-range rack" },
      "pairsWith": ["adjustable-bench", "olympic-barbell", "bumper-plates", "horse-stall-mat", "dip-attachment"]
    },
    {
      "id": "rep-pr1100",
      "name": "REP PR-1100 Power Rack",
      "brand": "REP Fitness",
      "tier": "mid",
      "price": 500,
      "priceDisplay": "$500",
      "asin": "B07KY515S9",
      "amazonUrl": "https://www.amazon.com/dp/B07KY515S9?tag=runbikecalc-20",
      "imageUrl": null,
      "imageMedium": null,
      "scores": {
        "goal_strength": 9, "goal_bodybuilding": 8, "goal_powerlifting": 6, "goal_functional": 6, "goal_general": 8,
        "exp_beginner": 8, "exp_intermediate": 9, "exp_advanced": 5,
        "lift_squat": 9, "lift_bench": 9, "lift_deadlift": 5, "lift_ohp": 8, "lift_pullup": 8,
        "space_compact": 5, "space_garage": 9, "space_dedicated": 9,
        "budget_under_500": 8, "budget_500_1000": 9, "budget_1000_2000": 5, "budget_over_2000": 2,
        "ceiling_under_8": 6, "ceiling_8_9": 9, "ceiling_over_9": 9
      },
      "specs": { "type": "Power Rack", "footprint": "48\" x 47\"", "height": "86\"", "weightCapacity": "700 lb", "pullUpBar": true, "jCups": true, "safetyBars": true },
      "verdict": { "garageGymReady": "YES", "bestFor": "REP quality at entry-level price" },
      "pairsWith": ["adjustable-bench", "olympic-barbell", "bumper-plates", "horse-stall-mat", "dip-attachment"]
    },
    {
      "id": "rogue-sml2",
      "name": "Rogue SML-2 Squat Stand",
      "brand": "Rogue",
      "tier": "mid",
      "price": 600,
      "priceDisplay": "$600",
      "amazonUrl": "https://www.amazon.com/s?k=Rogue+SML-2+Squat+Stand&tag=runbikecalc-20",
      "imageUrl": null,
      "imageMedium": null,
      "scores": {
        "goal_strength": 8, "goal_bodybuilding": 7, "goal_powerlifting": 7, "goal_functional": 7, "goal_general": 7,
        "exp_beginner": 6, "exp_intermediate": 8, "exp_advanced": 8,
        "lift_squat": 9, "lift_bench": 7, "lift_deadlift": 6, "lift_ohp": 9, "lift_pullup": 5,
        "space_compact": 9, "space_garage": 8, "space_dedicated": 7,
        "budget_under_500": 2, "budget_500_1000": 9, "budget_1000_2000": 6, "budget_over_2000": 3,
        "ceiling_under_8": 9, "ceiling_8_9": 9, "ceiling_over_9": 9
      },
      "specs": { "type": "Squat Stand", "footprint": "49\" x 48\"", "height": "92\"", "weightCapacity": "1000 lb", "pullUpBar": false, "jCups": true, "safetyBars": false },
      "verdict": { "garageGymReady": "YES", "bestFor": "Compact Rogue quality, no cage needed" },
      "pairsWith": ["flat-bench", "rogue-barbell", "bumper-plates", "horse-stall-mat"]
    },
    {
      "id": "rogue-rml390f",
      "name": "Rogue RML-390F Monster Lite Rack",
      "brand": "Rogue",
      "tier": "premium",
      "price": 1100,
      "priceDisplay": "$1,100",
      "amazonUrl": "https://www.amazon.com/s?k=Rogue+RML-390F+Monster+Lite+Rack&tag=runbikecalc-20",
      "imageUrl": null,
      "imageMedium": null,
      "scores": {
        "goal_strength": 10, "goal_bodybuilding": 9, "goal_powerlifting": 9, "goal_functional": 8, "goal_general": 8,
        "exp_beginner": 6, "exp_intermediate": 9, "exp_advanced": 10,
        "lift_squat": 10, "lift_bench": 10, "lift_deadlift": 6, "lift_ohp": 9, "lift_pullup": 10,
        "space_compact": 2, "space_garage": 9, "space_dedicated": 10,
        "budget_under_500": 0, "budget_500_1000": 3, "budget_1000_2000": 10, "budget_over_2000": 7,
        "ceiling_under_8": 4, "ceiling_8_9": 8, "ceiling_over_9": 10
      },
      "specs": { "type": "Full Power Rack", "footprint": "53\" x 49\"", "height": "90.375\"", "weightCapacity": "1000+ lb", "pullUpBar": true, "jCups": true, "safetyBars": true },
      "verdict": { "garageGymReady": "YES", "bestFor": "Best overall home gym rack - Rogue quality" },
      "pairsWith": ["adjustable-bench", "rogue-barbell", "bumper-plates", "horse-stall-mat", "dip-attachment"]
    },
    {
      "id": "rep-pr4000",
      "name": "REP PR-4000 Power Rack",
      "brand": "REP Fitness",
      "tier": "premium",
      "price": 900,
      "priceDisplay": "$900",
      "amazonUrl": "https://www.amazon.com/s?k=REP+PR-4000+Power+Rack&tag=runbikecalc-20",
      "imageUrl": null,
      "imageMedium": null,
      "scores": {
        "goal_strength": 10, "goal_bodybuilding": 9, "goal_powerlifting": 9, "goal_functional": 8, "goal_general": 8,
        "exp_beginner": 6, "exp_intermediate": 9, "exp_advanced": 10,
        "lift_squat": 10, "lift_bench": 10, "lift_deadlift": 6, "lift_ohp": 9, "lift_pullup": 10,
        "space_compact": 3, "space_garage": 9, "space_dedicated": 10,
        "budget_under_500": 0, "budget_500_1000": 8, "budget_1000_2000": 10, "budget_over_2000": 6,
        "ceiling_under_8": 5, "ceiling_8_9": 9, "ceiling_over_9": 10
      },
      "specs": { "type": "Full Power Rack", "footprint": "49\" x 48\"", "height": "93\"", "weightCapacity": "1000 lb", "pullUpBar": true, "jCups": true, "safetyBars": true },
      "verdict": { "garageGymReady": "YES", "bestFor": "Best value premium rack" },
      "pairsWith": ["adjustable-bench", "olympic-barbell", "bumper-plates", "horse-stall-mat", "dip-attachment"]
    },
    {
      "id": "titan-x3",
      "name": "Titan X-3 Series Flat Foot Rack",
      "brand": "Titan Fitness",
      "tier": "mid",
      "price": 650,
      "priceDisplay": "$650",
      "asin": "B09CLNPXR2",
      "amazonUrl": "https://www.amazon.com/dp/B09CLNPXR2?tag=runbikecalc-20",
      "imageUrl": null,
      "imageMedium": null,
      "scores": {
        "goal_strength": 9, "goal_bodybuilding": 8, "goal_powerlifting": 8, "goal_functional": 7, "goal_general": 8,
        "exp_beginner": 7, "exp_intermediate": 9, "exp_advanced": 8,
        "lift_squat": 10, "lift_bench": 9, "lift_deadlift": 5, "lift_ohp": 8, "lift_pullup": 9,
        "space_compact": 3, "space_garage": 9, "space_dedicated": 9,
        "budget_under_500": 2, "budget_500_1000": 9, "budget_1000_2000": 6, "budget_over_2000": 3,
        "ceiling_under_8": 5, "ceiling_8_9": 9, "ceiling_over_9": 9
      },
      "specs": { "type": "Full Power Rack", "footprint": "49\" x 48\"", "height": "91\"", "weightCapacity": "1100 lb", "pullUpBar": true, "jCups": true, "safetyBars": true },
      "verdict": { "garageGymReady": "YES", "bestFor": "Heavy-duty rack at mid-range price" },
      "pairsWith": ["adjustable-bench", "olympic-barbell", "bumper-plates", "horse-stall-mat", "dip-attachment"]
    },
    {
      "id": "prx-profile-rack",
      "name": "PRx Performance Profile Rack",
      "brand": "PRx",
      "tier": "compact",
      "price": 700,
      "priceDisplay": "$700",
      "asin": "B07BMG6RC8",
      "amazonUrl": "https://www.amazon.com/dp/B07BMG6RC8?tag=runbikecalc-20",
      "imageUrl": null,
      "imageMedium": null,
      "scores": {
        "goal_strength": 7, "goal_bodybuilding": 6, "goal_powerlifting": 5, "goal_functional": 7, "goal_general": 8,
        "exp_beginner": 7, "exp_intermediate": 8, "exp_advanced": 5,
        "lift_squat": 8, "lift_bench": 7, "lift_deadlift": 5, "lift_ohp": 7, "lift_pullup": 7,
        "space_compact": 10, "space_garage": 7, "space_dedicated": 5,
        "budget_under_500": 2, "budget_500_1000": 8, "budget_1000_2000": 5, "budget_over_2000": 2,
        "ceiling_under_8": 7, "ceiling_8_9": 9, "ceiling_over_9": 9
      },
      "specs": { "type": "Wall-Mounted Folding", "footprint": "22\" x 24\" (folded)", "height": "90\"", "weightCapacity": "1000 lb", "pullUpBar": true, "jCups": true, "safetyBars": false },
      "verdict": { "garageGymReady": "YES", "bestFor": "Folds flat to 4\" - best for shared spaces" },
      "pairsWith": ["flat-bench", "olympic-barbell", "bumper-plates"]
    },
    {
      "id": "rogue-rm4",
      "name": "Rogue RM-4 Monster Rack",
      "brand": "Rogue",
      "tier": "premium",
      "price": 2000,
      "priceDisplay": "$2,000+",
      "amazonUrl": "https://www.amazon.com/s?k=Rogue+RM-4+Monster+Rack&tag=runbikecalc-20",
      "imageUrl": null,
      "imageMedium": null,
      "scores": {
        "goal_strength": 10, "goal_bodybuilding": 9, "goal_powerlifting": 10, "goal_functional": 8, "goal_general": 7,
        "exp_beginner": 4, "exp_intermediate": 8, "exp_advanced": 10,
        "lift_squat": 10, "lift_bench": 10, "lift_deadlift": 6, "lift_ohp": 9, "lift_pullup": 10,
        "space_compact": 1, "space_garage": 7, "space_dedicated": 10,
        "budget_under_500": 0, "budget_500_1000": 0, "budget_1000_2000": 3, "budget_over_2000": 10,
        "ceiling_under_8": 2, "ceiling_8_9": 7, "ceiling_over_9": 10
      },
      "specs": { "type": "Monster Power Rack", "footprint": "53\" x 53\"", "height": "100\"", "weightCapacity": "1500+ lb", "pullUpBar": true, "jCups": true, "safetyBars": true },
      "verdict": { "garageGymReady": "YES", "bestFor": "Commercial-grade, unlimited upgrade path" },
      "pairsWith": ["adjustable-bench", "rogue-barbell", "bumper-plates", "horse-stall-mat", "dip-attachment"]
    },
    {
      "id": "valor-bd7",
      "name": "Valor Fitness BD-7 Power Rack",
      "brand": "Valor Fitness",
      "tier": "budget",
      "price": 350,
      "priceDisplay": "$350",
      "asin": "B002EJC990",
      "amazonUrl": "https://www.amazon.com/dp/B002EJC990?tag=runbikecalc-20",
      "imageUrl": null,
      "imageMedium": null,
      "scores": {
        "goal_strength": 7, "goal_bodybuilding": 7, "goal_powerlifting": 4, "goal_functional": 5, "goal_general": 7,
        "exp_beginner": 9, "exp_intermediate": 6, "exp_advanced": 3,
        "lift_squat": 8, "lift_bench": 7, "lift_deadlift": 4, "lift_ohp": 6, "lift_pullup": 7,
        "space_compact": 5, "space_garage": 8, "space_dedicated": 7,
        "budget_under_500": 10, "budget_500_1000": 6, "budget_1000_2000": 2, "budget_over_2000": 1,
        "ceiling_under_8": 7, "ceiling_8_9": 9, "ceiling_over_9": 8
      },
      "specs": { "type": "Power Rack", "footprint": "48\" x 42\"", "height": "83\"", "weightCapacity": "500 lb", "pullUpBar": true, "jCups": true, "safetyBars": true },
      "verdict": { "garageGymReady": "MAYBE", "bestFor": "Built-in lat pulldown option" },
      "pairsWith": ["flat-bench", "olympic-barbell", "bumper-plates"]
    },
    {
      "id": "bells-of-steel-light-commercial",
      "name": "Bells of Steel Light Commercial Rack",
      "brand": "Bells of Steel",
      "tier": "mid",
      "price": 750,
      "priceDisplay": "$750",
      "amazonUrl": "https://www.amazon.com/s?k=Bells+of+Steel+Light+Commercial+Power+Rack&tag=runbikecalc-20",
      "imageUrl": null,
      "imageMedium": null,
      "scores": {
        "goal_strength": 9, "goal_bodybuilding": 8, "goal_powerlifting": 8, "goal_functional": 7, "goal_general": 8,
        "exp_beginner": 7, "exp_intermediate": 9, "exp_advanced": 8,
        "lift_squat": 10, "lift_bench": 9, "lift_deadlift": 5, "lift_ohp": 8, "lift_pullup": 9,
        "space_compact": 4, "space_garage": 9, "space_dedicated": 9,
        "budget_under_500": 2, "budget_500_1000": 9, "budget_1000_2000": 6, "budget_over_2000": 3,
        "ceiling_under_8": 5, "ceiling_8_9": 9, "ceiling_over_9": 9
      },
      "specs": { "type": "Full Power Rack", "footprint": "48\" x 48\"", "height": "90\"", "weightCapacity": "1000 lb", "pullUpBar": true, "jCups": true, "safetyBars": true },
      "verdict": { "garageGymReady": "YES", "bestFor": "Excellent build quality, Canadian brand" },
      "pairsWith": ["adjustable-bench", "olympic-barbell", "bumper-plates", "horse-stall-mat", "dip-attachment"]
    },
    {
      "id": "rep-squat-stand",
      "name": "REP SR-4000 Squat Rack",
      "brand": "REP Fitness",
      "tier": "compact",
      "price": 400,
      "priceDisplay": "$400",
      "amazonUrl": "https://www.amazon.com/s?k=REP+SR-4000+Squat+Rack&tag=runbikecalc-20",
      "imageUrl": null,
      "imageMedium": null,
      "scores": {
        "goal_strength": 7, "goal_bodybuilding": 6, "goal_powerlifting": 6, "goal_functional": 7, "goal_general": 7,
        "exp_beginner": 7, "exp_intermediate": 8, "exp_advanced": 6,
        "lift_squat": 8, "lift_bench": 6, "lift_deadlift": 6, "lift_ohp": 8, "lift_pullup": 5,
        "space_compact": 9, "space_garage": 8, "space_dedicated": 6,
        "budget_under_500": 9, "budget_500_1000": 7, "budget_1000_2000": 3, "budget_over_2000": 1,
        "ceiling_under_8": 8, "ceiling_8_9": 9, "ceiling_over_9": 9
      },
      "specs": { "type": "Squat Stand", "footprint": "48\" x 38\"", "height": "92\"", "weightCapacity": "1000 lb", "pullUpBar": false, "jCups": true, "safetyBars": false },
      "verdict": { "garageGymReady": "YES", "bestFor": "Compact squat stand, add spotter arms" },
      "pairsWith": ["flat-bench", "olympic-barbell", "bumper-plates"]
    },
    {
      "id": "rogue-rml490",
      "name": "Rogue RML-490 Power Rack",
      "brand": "Rogue",
      "tier": "premium",
      "price": 1400,
      "priceDisplay": "$1,400",
      "amazonUrl": "https://www.amazon.com/s?k=Rogue+RML-490+Power+Rack&tag=runbikecalc-20",
      "imageUrl": null,
      "imageMedium": null,
      "scores": {
        "goal_strength": 10, "goal_bodybuilding": 9, "goal_powerlifting": 10, "goal_functional": 8, "goal_general": 8,
        "exp_beginner": 5, "exp_intermediate": 9, "exp_advanced": 10,
        "lift_squat": 10, "lift_bench": 10, "lift_deadlift": 6, "lift_ohp": 9, "lift_pullup": 10,
        "space_compact": 2, "space_garage": 8, "space_dedicated": 10,
        "budget_under_500": 0, "budget_500_1000": 2, "budget_1000_2000": 9, "budget_over_2000": 7,
        "ceiling_under_8": 3, "ceiling_8_9": 8, "ceiling_over_9": 10
      },
      "specs": { "type": "Full Power Rack (6-post)", "footprint": "53\" x 78\"", "height": "90\"", "weightCapacity": "1000+ lb", "pullUpBar": true, "jCups": true, "safetyBars": true },
      "verdict": { "garageGymReady": "YES", "bestFor": "6-post design for serious lifters" },
      "pairsWith": ["adjustable-bench", "rogue-barbell", "bumper-plates", "horse-stall-mat", "dip-attachment"]
    }
  ],
  "accessories": [
    { "id": "flat-bench", "name": "Amazon Basics Flat Weight Bench", "priceDisplay": "$55", "asin": "B072Z1WN4S", "amazonUrl": "https://www.amazon.com/dp/B072Z1WN4S?tag=runbikecalc-20", "imageUrl": null, "imageMedium": null },
    { "id": "adjustable-bench", "name": "REP AB-3000 Adjustable Bench", "priceDisplay": "$300", "asin": "B00YNS7D9G", "amazonUrl": "https://www.amazon.com/dp/B00YNS7D9G?tag=runbikecalc-20", "imageUrl": null, "imageMedium": null },
    { "id": "olympic-barbell", "name": "CAP Barbell Olympic Bar (7ft)", "priceDisplay": "$120", "asin": "B07D3Q7NGJ", "amazonUrl": "https://www.amazon.com/dp/B07D3Q7NGJ?tag=runbikecalc-20", "imageUrl": null, "imageMedium": null },
    { "id": "rogue-barbell", "name": "Rogue Ohio Bar", "priceDisplay": "$295", "amazonUrl": "https://www.amazon.com/s?k=Rogue+Ohio+Bar&tag=runbikecalc-20", "imageUrl": null, "imageMedium": null },
    { "id": "bumper-plates", "name": "Bumper Plate Set (260 lb)", "priceDisplay": "$350", "asin": "B01J2J0PJ0", "amazonUrl": "https://www.amazon.com/dp/B01J2J0PJ0?tag=runbikecalc-20", "imageUrl": null, "imageMedium": null },
    { "id": "horse-stall-mat", "name": "Horse Stall Mat (4x6 ft)", "priceDisplay": "$50", "asin": "B07CNLLZGP", "amazonUrl": "https://www.amazon.com/dp/B07CNLLZGP?tag=runbikecalc-20", "imageUrl": null, "imageMedium": null },
    { "id": "dip-attachment", "name": "Power Rack Dip Attachment", "priceDisplay": "$60", "asin": "B0BGHJVXV7", "amazonUrl": "https://www.amazon.com/dp/B0BGHJVXV7?tag=runbikecalc-20", "imageUrl": null, "imageMedium": null }
  ]
}
